objexplore/__init__.py
objexplore/cached_object.py
objexplore/config.py
objexplore/explorer.py
objexplore/filter.py
objexplore/help_layout.py
objexplore/objexplore.py
objexplore/overview.py
objexplore/stack.py
objexplore/utils.py
objexplore-1.6.3.dist-info/LICENSE
objexplore-1.6.3.dist-info/METADATA
objexplore-1.6.3.dist-info/WHEEL
objexplore-1.6.3.dist-info/top_level.txt
objexplore-1.6.3.dist-info/RECORD
