Metadata-Version: 2.1
Name: objexplore
Version: 1.6.3
Summary: Interactive Python Object Explorer
Home-page: https://github.com/kylepollina/objexplore
Author: Kyle Pollina
Author-email: kylepollina@pm.me
License: UNKNOWN
Platform: UNKNOWN
Classifier: Programming Language :: Python :: 3
Classifier: Programming Language :: Python :: 3.7
Classifier: Programming Language :: Python :: 3.8
Classifier: Programming Language :: Python :: 3.9
